pybankers/__init__.py
pybankers/__main__.py
pybankers/pybankers.py
pybankers-1.0.2.dist-info/LICENSE
pybankers-1.0.2.dist-info/METADATA
pybankers-1.0.2.dist-info/WHEEL
pybankers-1.0.2.dist-info/top_level.txt
pybankers-1.0.2.dist-info/RECORD
